{
    "domain": "confiant-integrations.global.ssl.fastly.net",
    "owner": {
        "name": "Fastly, Inc.",
        "displayName": "Fastly",
        "privacyPolicy": "https://www.fastly.com/privacy",
        "url": "http://fastly.com"
    },
    "source": [
        "DuckDuckGo-CA"
    ],
    "prevalence": 0.0253,
    "sites": 246,
    "subdomains": [],
    "cnames": [],
    "fingerprinting": 1,
    "resources": [
        {
            "rule": "confiant-integrations\\.global\\.ssl\\.fastly\\.net\\/gpt_v3l\\/202009141015\\/wrap\\.js",
            "cookies": 0,
            "fingerprinting": 1,
            "subdomains": [],
            "apis": {
                "Navigator.prototype.userAgent": 50,
                "Date.prototype.getTime": 6
            },
            "sites": 96,
            "prevalence": 0.00986,
            "cnames": [],
            "responseHashes": [
                "4c8fc74b2dd28bcd3ba6c6b25ed7215ed3d15022a4f023f592e350f82dfca775"
            ],
            "type": "Script",
            "exampleSites": [
                "forums.macrumors.com",
                "heavy.com",
                "thoughtcatalog.com",
                "www.usatoday.com",
                "www.trippy.com",
                "www.cheatcc.com",
                "gardenerspath.com",
                "www.behindthevoiceactors.com",
                "www.campgroundreviews.com",
                "www.doityourselfrv.com",
                "www.diynatural.com",
                "pynative.com",
                "www.homestratosphere.com",
                "wellnessmama.com",
                "www.mtgsalvation.com",
                "www.nerdsandscoundrels.com",
                "www.halfbakedharvest.com",
                "bestofmachinery.com",
                "thehappypuppysite.com",
                "www.k9ofmine.com"
            ]
        },
        {
            "rule": "confiant-integrations\\.global\\.ssl\\.fastly\\.net\\/gpt\\/202009141015\\/wrap\\.js",
            "cookies": 0,
            "fingerprinting": 1,
            "subdomains": [],
            "apis": {
                "Navigator.prototype.userAgent": 84,
                "Date.prototype.getTime": 48
            },
            "sites": 119,
            "prevalence": 0.0122,
            "cnames": [],
            "responseHashes": [
                "8a7e7b4c40727a065b2f140043b4778829b5f2175ce5c7e032164c3e91d8ffaa"
            ],
            "type": "Script",
            "exampleSites": [
                "download.cnet.com",
                "knowyourmeme.com",
                "www.bustle.com",
                "www.businessinsider.com",
                "www.cbssports.com",
                "www.cbsnews.com",
                "www.cnet.com",
                "www.discogs.com",
                "www.dummies.com",
                "www.latimes.com",
                "www.fodors.com",
                "fox8.com",
                "popculture.com",
                "www.pinknews.co.uk",
                "www.stack.com",
                "www.thecarconnection.com",
                "advrider.com",
                "www.nydailynews.com",
                "socialblade.com",
                "golfweek.usatoday.com"
            ]
        },
        {
            "rule": "confiant-integrations\\.global\\.ssl\\.fastly\\.net\\/prebid\\/202009141015\\/wrap\\.js",
            "cookies": 0,
            "fingerprinting": 1,
            "subdomains": [],
            "apis": {
                "Navigator.prototype.userAgent": 79
            },
            "sites": 86,
            "prevalence": 0.00883,
            "cnames": [],
            "responseHashes": [
                "c7a3a99eb4907e4985873bcc4f85c1283c0c99c5764edc4dc07a3a22a0f86875"
            ],
            "type": "Script",
            "exampleSites": [
                "download.cnet.com",
                "knowyourmeme.com",
                "www.businessinsider.com",
                "www.cbssports.com",
                "www.cbsnews.com",
                "www.cnet.com",
                "www.discogs.com",
                "www.dummies.com",
                "www.theguardian.com",
                "www.tvguide.com",
                "www.netmums.com",
                "www.lawlessfrench.com",
                "spectator.org",
                "www.smartrvguide.com",
                "www.mlb.com",
                "www.wfla.com",
                "babylonbee.com",
                "celebpie.com",
                "www.alternet.org",
                "files.minecraftforge.net"
            ]
        },
        {
            "rule": "confiant-integrations\\.global\\.ssl\\.fastly\\.net\\/prebid_v3l\\/202003181643\\/wrap\\.js",
            "cookies": 0,
            "fingerprinting": 1,
            "subdomains": [],
            "apis": {
                "Navigator.prototype.userAgent": 4
            },
            "sites": 4,
            "prevalence": 0.000411,
            "cnames": [],
            "responseHashes": [
                "0cdfd11eeff2c617a795c4e0404e2c9fe3a200bf0ea64dbde36737a7046e8a26"
            ],
            "type": "Script",
            "exampleSites": [
                "tazzaz.com",
                "www.astro.com",
                "www.babelio.com",
                "www.marketscreener.com"
            ]
        }
    ],
    "categories": [
        "Ad Motivated Tracking",
        "Advertising",
        "Analytics",
        "Third-Party Analytics Marketing",
        "Action Pixels",
        "CDN",
        "Embedded Content",
        "Session Replay"
    ],
    "performance": {},
    "cookies": 0,
    "types": {
        "Script": 305
    }
}