{
    "domain": "foxycart.com",
    "owner": {},
    "source": [
        "DuckDuckGo-CA"
    ],
    "prevalence": 0.000205,
    "sites": 2,
    "subdomains": [
        "brookings",
        "churchmilitant"
    ],
    "cnames": [],
    "fingerprinting": 1,
    "resources": [
        {
            "rule": "foxycart\\.com\\/cart",
            "cookies": 0.000307,
            "fingerprinting": 0,
            "subdomains": [
                "brookings",
                "churchmilitant"
            ],
            "apis": {},
            "sites": 3,
            "prevalence": 0.000307,
            "cnames": [],
            "responseHashes": [
                "3bfd01e70ed7de479142be5ac5a995c7d045b4d53a7ed7d1d8f14c62651f6844",
                "ec3358471ff08575b47fb231cafc2947a7214c147e4c17ba487a66a1ba76b93c"
            ]
        }
    ],
    "categories": [],
    "performance": {
        "time": 0,
        "size": 0,
        "cpu": 0,
        "cache": 1
    },
    "cookies": 0.000205,
    "types": {
        "Script": 3
    }
}