{
    "domain": "mfadsrvr.com",
    "owner": {
        "name": "IPONWEB GmbH",
        "displayName": "IPONWEB",
        "privacyPolicy": "https://www.iponweb.com/privacy-policy/",
        "url": "http://iponweb.com"
    },
    "source": [
        "DuckDuckGo-CH"
    ],
    "prevalence": 0.018,
    "sites": 174,
    "subdomains": [
        "rtb"
    ],
    "cnames": [],
    "fingerprinting": 0,
    "resources": [
        {
            "rule": "mfadsrvr\\.com\\/sync",
            "cookies": 0.0149,
            "fingerprinting": 0,
            "subdomains": [
                "rtb"
            ],
            "apis": {},
            "sites": 175,
            "prevalence": 0.0181,
            "cnames": [],
            "responseHashes": [
                "548f2d6f4d0d820c6c5ffbeffcbd7f0e73193e2932eefe542accc84762deec87",
                "b1442e85b03bdcaf66dc58c7abb98745dd2687d86350be9a298a1d9382ac849b"
            ],
            "type": "Image",
            "exampleSites": [
                "abcnews.go.com",
                "arstechnica.com",
                "drudgereport.com",
                "forum.wordreference.com",
                "globalnews.ca",
                "health.usnews.com",
                "mashable.com",
                "money.cnn.com",
                "people.com",
                "pjmedia.com",
                "www.breitbart.com",
                "weather.com",
                "administrator.de",
                "www.politifact.com",
                "teslamag.de",
                "mydramalist.com",
                "vim.fandom.com",
                "www.gazetatema.net",
                "www.minecraftforum.net",
                "radikal.ru"
            ]
        },
        {
            "rule": "mfadsrvr\\.com\\/ul_cb\\/sync",
            "cookies": 0.0135,
            "fingerprinting": 0,
            "subdomains": [
                "rtb"
            ],
            "apis": {},
            "sites": 140,
            "prevalence": 0.0144,
            "cnames": [],
            "responseHashes": [
                "6adc3d4c1056996e4e8b765a62604c78b1f867cceb3b15d0b9bedb7c4857f992",
                "579a172ca2c700734ebcfa06d105a134f31ec2357660e58e0874cfdee8472fd4"
            ],
            "type": "Image",
            "exampleSites": [
                "abcnews.go.com",
                "arstechnica.com",
                "drudgereport.com",
                "forum.wordreference.com",
                "globalnews.ca",
                "mashable.com",
                "money.cnn.com",
                "people.com",
                "pjmedia.com",
                "screenrant.com",
                "www.theweathernetwork.com",
                "www.howtopronounce.com",
                "www.macwelt.de",
                "www.vanityfair.com",
                "coincentral.com",
                "www.newyorker.com",
                "www.liveleak.com",
                "armorgames.com",
                "forum.lefigaro.fr",
                "www.tampabay.com"
            ]
        }
    ],
    "categories": [
        "Ad Motivated Tracking",
        "Advertising",
        "Ad Fraud"
    ],
    "performance": {
        "time": 1,
        "size": 1,
        "cpu": 0,
        "cache": 3
    },
    "cookies": 0.015,
    "types": {
        "Image": 315
    }
}