{
    "domain": "openx.net",
    "owner": {
        "name": "OpenX Technologies Inc",
        "displayName": "OpenX",
        "privacyPolicy": "https://www.openx.com/legal/privacy-policy/",
        "url": "http://openx.com"
    },
    "source": [
        "DuckDuckGo-NO"
    ],
    "prevalence": 0.512,
    "sites": 4966,
    "subdomains": [
        "eu-u",
        "us-u",
        "rtb",
        "freestar-d",
        "curse-d",
        "buysellads-d",
        "snigel-d",
        "playwire-d",
        "aufeminin-e-d",
        "mcclatchy-d",
        "enthusiast-gaming-d",
        "os4m-d",
        "u",
        "rock-you-d",
        "adpushup-d",
        "meredith-d",
        "townsquaremedia-d",
        "teachingaids-d",
        "wikia-d",
        "pubgalaxy-d",
        "mediatradecraft-d",
        "hsw-d",
        "ninegag-d",
        "carambola-d",
        "pubwise-d",
        "condenastus-d",
        "dailykos-d",
        "ggsoftware-d",
        "adnimation2-d",
        "nineto5mac-d",
        "hereisthecity-d",
        "microsoft-aunz-d",
        "addkt-d",
        "thedrive-d",
        "onscroll-d",
        "burdaforward-d",
        "pixfuture2-d",
        "cosmicshovel-d",
        "pmc-d",
        "evolvemedia-d",
        "aarp-d",
        "adnimation-d",
        "snopes-d",
        "massarius-d",
        "cafemedia-d",
        "borderblue-d",
        "ookla-d",
        "ziffdavis-d",
        "adnet-d",
        "exceljet-d",
        "thechive-d",
        "yieldbird-d",
        "bloggernetwork-d",
        "the-eighth-d",
        "streamamp-d",
        "nationalreview-d",
        "ezoic-d",
        "netpoint-d",
        "tradehouse-d",
        "ami-d",
        "lifehack-d",
        "kongregate-d",
        "ascendeum-d",
        "hearstnewspapers-d",
        "axel-springer-d",
        "epoch-times-d",
        "pbhmedia-d",
        "ultimate-guitar-d",
        "upi-d",
        "salemwebnetworks-d",
        "traffective-d",
        "stands4-d",
        "onlineadvertisingsolutions-d",
        "publisherdesk-d",
        "cookpad-d",
        "msodigital-d",
        "scmp-d",
        "coinmarketcap-d",
        "spolecznosci-d",
        "nypost-d",
        "networkn-d",
        "gremi-d",
        "perezhilton-d",
        "yieldlove-d",
        "monetizemore-d",
        "realtor-d",
        "business-insider-d",
        "select-d",
        "dominionmedia-d",
        "eurosport-d",
        "indexhr-d",
        "wordreference-d",
        "insticator-d",
        "setupad-d",
        "sporcle-d",
        "moneytizer-d",
        "merriamwebster-d",
        "drugs-d",
        "ask-d",
        "newsnow-d",
        "guardian-d",
        "oneadvertising-d",
        "adpone-d",
        "worldstarhiphop-d",
        "mansueto-d",
        "gift-connect-d",
        "outbrain-d",
        "distroscale-d",
        "viumbe-d",
        "anyclip-d",
        "primis-d",
        "farlex-d",
        "taboola-d",
        "videointelligence-d",
        "vidoomy-d",
        "one-and-one-d",
        "oao-d",
        "zergnet-d",
        "reddit-d",
        "yellowpages-d",
        "timeanddate-d",
        "webfinance-d",
        "theblaze2-d",
        "ruptly-d"
    ],
    "cnames": [],
    "fingerprinting": 1,
    "resources": [
        {
            "rule": "openx\\.net\\/w\\/1\\.0\\/sd",
            "cookies": 0.0175,
            "fingerprinting": 0,
            "subdomains": [
                "eu-u",
                "us-u"
            ],
            "apis": {},
            "sites": 2631,
            "prevalence": 0.271,
            "cnames": [],
            "type": "Image"
        },
        {
            "rule": "openx\\.net\\/sync\\/dds",
            "cookies": 0.0406,
            "fingerprinting": 0,
            "subdomains": [
                "rtb"
            ],
            "apis": {},
            "sites": 1489,
            "prevalence": 0.154,
            "cnames": [],
            "type": "Image"
        },
        {
            "rule": "openx\\.net\\/w\\/1\\.0\\/arj",
            "cookies": 0.077,
            "fingerprinting": 0,
            "subdomains": [
                "freestar-d",
                "curse-d",
                "buysellads-d",
                "snigel-d",
                "playwire-d",
                "aufeminin-e-d",
                "mcclatchy-d",
                "enthusiast-gaming-d",
                "os4m-d",
                "u",
                "rock-you-d",
                "adpushup-d",
                "meredith-d",
                "townsquaremedia-d",
                "teachingaids-d",
                "wikia-d",
                "pubgalaxy-d",
                "mediatradecraft-d",
                "hsw-d",
                "ninegag-d",
                "carambola-d",
                "pubwise-d",
                "condenastus-d",
                "dailykos-d",
                "ggsoftware-d",
                "adnimation2-d",
                "nineto5mac-d",
                "hereisthecity-d",
                "microsoft-aunz-d",
                "addkt-d",
                "thedrive-d",
                "onscroll-d",
                "burdaforward-d",
                "pixfuture2-d",
                "cosmicshovel-d",
                "pmc-d",
                "evolvemedia-d",
                "aarp-d",
                "adnimation-d",
                "snopes-d",
                "massarius-d",
                "cafemedia-d",
                "borderblue-d",
                "ookla-d",
                "ziffdavis-d",
                "adnet-d",
                "exceljet-d",
                "thechive-d",
                "yieldbird-d",
                "bloggernetwork-d",
                "the-eighth-d",
                "streamamp-d",
                "nationalreview-d",
                "ezoic-d",
                "netpoint-d",
                "tradehouse-d",
                "ami-d",
                "lifehack-d",
                "kongregate-d",
                "ascendeum-d",
                "hearstnewspapers-d",
                "axel-springer-d",
                "epoch-times-d",
                "pbhmedia-d",
                "ultimate-guitar-d",
                "upi-d",
                "salemwebnetworks-d",
                "traffective-d",
                "stands4-d",
                "onlineadvertisingsolutions-d",
                "publisherdesk-d",
                "cookpad-d",
                "msodigital-d",
                "scmp-d",
                "coinmarketcap-d",
                "spolecznosci-d",
                "nypost-d",
                "networkn-d",
                "gremi-d",
                "perezhilton-d",
                "yieldlove-d",
                "monetizemore-d",
                "realtor-d",
                "business-insider-d",
                "select-d",
                "dominionmedia-d",
                "eurosport-d",
                "indexhr-d",
                "wordreference-d",
                "insticator-d",
                "setupad-d",
                "sporcle-d",
                "moneytizer-d",
                "merriamwebster-d",
                "drugs-d",
                "ask-d",
                "newsnow-d",
                "guardian-d",
                "oneadvertising-d",
                "adpone-d",
                "worldstarhiphop-d",
                "mansueto-d"
            ],
            "apis": {},
            "sites": 1067,
            "prevalence": 0.11,
            "cnames": [],
            "type": "XHR"
        },
        {
            "rule": "openx\\.net\\/w\\/1\\.0\\/cm",
            "cookies": 0.103,
            "fingerprinting": 0,
            "subdomains": [
                "us-u",
                "u",
                "eu-u"
            ],
            "apis": {},
            "sites": 1464,
            "prevalence": 0.151,
            "cnames": [],
            "type": "Image"
        },
        {
            "rule": "openx\\.net\\/w\\/1\\.0\\/cm",
            "cookies": 0.0549,
            "fingerprinting": 0,
            "subdomains": [
                "us-u",
                "u",
                "gift-connect-d"
            ],
            "apis": {},
            "sites": 794,
            "prevalence": 0.0819,
            "cnames": [],
            "type": "Document"
        },
        {
            "rule": "openx\\.net\\/w\\/1\\.0\\/pd",
            "cookies": 0.0457,
            "fingerprinting": 0,
            "subdomains": [
                "eu-u",
                "u"
            ],
            "apis": {},
            "sites": 656,
            "prevalence": 0.0676,
            "cnames": [],
            "type": "Document"
        },
        {
            "rule": "openx\\.net\\/sync\\/prebid",
            "cookies": 0.00144,
            "fingerprinting": 0,
            "subdomains": [
                "rtb"
            ],
            "apis": {},
            "sites": 38,
            "prevalence": 0.00392,
            "cnames": [],
            "type": "Image"
        },
        {
            "rule": "openx\\.net\\/w\\/1\\.0\\/pd",
            "cookies": 0.0169,
            "fingerprinting": 0,
            "subdomains": [
                "eu-u",
                "u"
            ],
            "apis": {},
            "sites": 245,
            "prevalence": 0.0253,
            "cnames": [],
            "type": "Image"
        },
        {
            "rule": "openx\\.net\\/v\\/1\\.0\\/avjp",
            "cookies": 0.0159,
            "fingerprinting": 0,
            "subdomains": [
                "outbrain-d",
                "enthusiast-gaming-d",
                "gift-connect-d",
                "select-d",
                "teachingaids-d",
                "distroscale-d",
                "viumbe-d",
                "cafemedia-d",
                "anyclip-d",
                "primis-d",
                "farlex-d",
                "playwire-d"
            ],
            "apis": {},
            "sites": 199,
            "prevalence": 0.0205,
            "cnames": [],
            "type": "XHR"
        },
        {
            "rule": "openx\\.net\\/v\\/1\\.0\\/av",
            "cookies": 0.00546,
            "fingerprinting": 0,
            "subdomains": [
                "taboola-d",
                "videointelligence-d",
                "vidoomy-d"
            ],
            "apis": {},
            "sites": 91,
            "prevalence": 0.00938,
            "cnames": [],
            "type": "XHR"
        },
        {
            "rule": "openx\\.net\\/w\\/1\\.0\\/jstag",
            "cookies": 0,
            "fingerprinting": 1,
            "subdomains": [
                "one-and-one-d",
                "oao-d",
                "borderblue-d",
                "zergnet-d",
                "reddit-d",
                "yellowpages-d",
                "timeanddate-d",
                "webfinance-d",
                "theblaze2-d",
                "tradehouse-d",
                "carambola-d"
            ],
            "apis": {
                "Navigator.prototype.userAgent": 1,
                "Navigator.prototype.appName": 1,
                "window.localStorage": 1,
                "Navigator.prototype.platform": 1,
                "Navigator.prototype.plugins": 1,
                "Screen.prototype.width": 1,
                "Screen.prototype.height": 1,
                "Screen.prototype.colorDepth": 1,
                "Date.prototype.getTimezoneOffset": 1,
                "Date.prototype.getTime": 1
            },
            "sites": 36,
            "prevalence": 0.00371,
            "cnames": [],
            "type": "Script"
        },
        {
            "rule": "openx\\.net\\/mw\\/1\\.0\\/jstag",
            "cookies": 0.000412,
            "fingerprinting": 2,
            "subdomains": [
                "farlex-d"
            ],
            "apis": {
                "Navigator.prototype.userAgent": 7,
                "Navigator.prototype.appName": 7,
                "window.localStorage": 7,
                "Navigator.prototype.platform": 7,
                "Navigator.prototype.plugins": 7,
                "Screen.prototype.width": 6,
                "Screen.prototype.height": 6,
                "Screen.prototype.colorDepth": 6,
                "Date.prototype.getTimezoneOffset": 6,
                "Date.prototype.getTime": 6,
                "Document.cookie getter": 4,
                "Document.cookie setter": 4
            },
            "sites": 16,
            "prevalence": 0.00165,
            "cnames": [],
            "type": "Script"
        },
        {
            "rule": "openx\\.net\\/mw\\/1\\.0\\/acj",
            "cookies": 0.00227,
            "fingerprinting": 0,
            "subdomains": [
                "farlex-d"
            ],
            "apis": {},
            "sites": 22,
            "prevalence": 0.00227,
            "cnames": [],
            "type": "Script"
        },
        {
            "rule": "openx\\.net\\/sync\\/prebid",
            "cookies": 0.000515,
            "fingerprinting": 0,
            "subdomains": [
                "rtb"
            ],
            "apis": {},
            "sites": 47,
            "prevalence": 0.00485,
            "cnames": [],
            "type": "Document"
        },
        {
            "rule": "openx\\.net\\/w\\/1\\.0\\/acj",
            "cookies": 0.00227,
            "fingerprinting": 0,
            "subdomains": [
                "tradehouse-d",
                "reddit-d",
                "borderblue-d",
                "timeanddate-d",
                "carambola-d"
            ],
            "apis": {},
            "sites": 26,
            "prevalence": 0.00268,
            "cnames": [],
            "type": "Script"
        },
        {
            "rule": "openx\\.net\\/w\\/1\\.0\\/acj",
            "cookies": 0.000412,
            "fingerprinting": 0,
            "subdomains": [
                "theblaze2-d",
                "webfinance-d",
                "oao-d",
                "ruptly-d"
            ],
            "apis": {},
            "sites": 12,
            "prevalence": 0.00124,
            "cnames": [],
            "type": "XHR"
        }
    ],
    "categories": [
        "Ad Motivated Tracking",
        "Advertising",
        "Ad Fraud",
        "Audience Measurement"
    ],
    "performance": {
        "time": 1,
        "size": 1,
        "cpu": 0,
        "cache": 3
    },
    "cookies": 0.274,
    "types": {
        "Image": 5867,
        "XHR": 1369,
        "Document": 1497,
        "Script": 100
    }
}