{
    "domain": "banned.video",
    "owner": {},
    "source": [
        "DuckDuckGo-US"
    ],
    "prevalence": 0.000118,
    "sites": 17,
    "subdomains": [
        "api",
        "downloads"
    ],
    "cnames": [],
    "fingerprinting": 0,
    "resources": [
        {
            "rule": "banned\\.video\\/graphql",
            "cookies": 0.0000208,
            "fingerprinting": 0,
            "subdomains": [
                "api"
            ],
            "apis": {},
            "sites": 3,
            "prevalence": 0.0000208,
            "cnames": [],
            "responseHashes": [],
            "type": "Preflight",
            "firstPartyCookies": {},
            "firstPartyCookiesSent": {},
            "exampleSites": [
                "2020electioncenter.com",
                "79days.news",
                "censoredbyjack.com"
            ]
        },
        {
            "rule": "banned\\.video\\/graphql",
            "cookies": 0,
            "fingerprinting": 0,
            "subdomains": [
                "api"
            ],
            "apis": {},
            "sites": 3,
            "prevalence": 0.0000208,
            "cnames": [],
            "responseHashes": [],
            "type": "Fetch",
            "firstPartyCookies": {},
            "firstPartyCookiesSent": {},
            "exampleSites": [
                "2020electioncenter.com",
                "79days.news",
                "censoredbyjack.com"
            ]
        },
        {
            "rule": "banned\\.video\\/videos\\/4eacf3f0-ef7c-473b-81da-b734eea8d868\\.mp4",
            "cookies": 0,
            "fingerprinting": 0,
            "subdomains": [
                "downloads"
            ],
            "apis": {},
            "sites": 2,
            "prevalence": 0.0000139,
            "cnames": [],
            "responseHashes": [],
            "type": "Media",
            "firstPartyCookies": {},
            "firstPartyCookiesSent": {},
            "exampleSites": [
                "wordpress.com",
                "lissahumanelife.wordpress.com"
            ]
        },
        {
            "rule": "banned\\.video\\/embed\\/5b92a1e6568f22455f55be2b",
            "cookies": 0.0000278,
            "fingerprinting": 0,
            "subdomains": [
                "api"
            ],
            "apis": {},
            "sites": 4,
            "prevalence": 0.0000278,
            "cnames": [],
            "responseHashes": [],
            "type": "Document",
            "firstPartyCookies": {},
            "firstPartyCookiesSent": {},
            "exampleSites": [
                "madashellnews.com",
                "www.infowars.com",
                "www.newswars.com",
                "www.prisonplanet.com"
            ]
        },
        {
            "rule": "banned\\.video\\/embed\\/5b9301832abf762e22bc22ff",
            "cookies": 0.0000139,
            "fingerprinting": 0,
            "subdomains": [
                "api"
            ],
            "apis": {},
            "sites": 2,
            "prevalence": 0.0000139,
            "cnames": [],
            "responseHashes": [],
            "type": "Document",
            "firstPartyCookies": {},
            "firstPartyCookiesSent": {},
            "exampleSites": [
                "madashellnews.com",
                "www.newswars.com"
            ]
        },
        {
            "rule": "banned\\.video\\/embed\\/5c59c724f7c188001c3d8e2f",
            "cookies": 0.0000139,
            "fingerprinting": 0,
            "subdomains": [
                "api"
            ],
            "apis": {},
            "sites": 2,
            "prevalence": 0.0000139,
            "cnames": [],
            "responseHashes": [],
            "type": "Document",
            "firstPartyCookies": {},
            "firstPartyCookiesSent": {},
            "exampleSites": [
                "newswars.com",
                "www.newswars.com"
            ]
        }
    ],
    "categories": [],
    "performance": {
        "time": 0,
        "size": 0,
        "cpu": 0,
        "cache": 0
    },
    "cookies": 0.000111,
    "types": {
        "Preflight": 3,
        "Fetch": 3,
        "Media": 2,
        "Document": 8
    },
    "nameservers": [
        "robin.ns.cloudflare.com",
        "merlin.ns.cloudflare.com"
    ]
}