{
    "domain": "brazzersexxxpornhd.com",
    "owner": {},
    "source": [
        "DuckDuckGo-US"
    ],
    "prevalence": 0.0000347,
    "sites": 5,
    "subdomains": [
        "www"
    ],
    "cnames": [],
    "fingerprinting": 0,
    "resources": [
        {
            "rule": "brazzersexxxpornhd\\.com\\/uploads\\/logotype\\.png",
            "cookies": 0.0000139,
            "fingerprinting": 0,
            "subdomains": [
                "www"
            ],
            "apis": {},
            "sites": 2,
            "prevalence": 0.0000139,
            "cnames": [],
            "responseHashes": [
                "e85e1fdb174d851d0677cb95f27b4842c13937da854940935ced1d1321ffdb32"
            ],
            "type": "Image",
            "firstPartyCookies": {},
            "firstPartyCookiesSent": {},
            "exampleSites": [
                "666xvideos.com",
                "www.666xvideos.com"
            ]
        },
        {
            "rule": "brazzersexxxpornhd\\.com\\/uploads\\/loading\\.jpg",
            "cookies": 0.0000277,
            "fingerprinting": 0,
            "subdomains": [],
            "apis": {},
            "sites": 4,
            "prevalence": 0.0000277,
            "cnames": [],
            "responseHashes": [
                "f48c003f8c5390dcd25a760da495991a53b40046d63e8a64073cb4157b40dd28"
            ],
            "type": "Image",
            "firstPartyCookies": {},
            "firstPartyCookiesSent": {},
            "exampleSites": [
                "666xvideos.com",
                "www.666xvideos.com",
                "www.brazzer.porn",
                "www.brazzers.download"
            ]
        }
    ],
    "categories": [],
    "performance": {},
    "cookies": 0.0000347,
    "types": {
        "Image": 6
    },
    "nameservers": [
        "arushi.ns.cloudflare.com",
        "bowen.ns.cloudflare.com"
    ]
}