{
    "domain": "growdiaries.com",
    "owner": {},
    "source": [
        "DuckDuckGo-US"
    ],
    "prevalence": 0.000073,
    "sites": 10,
    "subdomains": [],
    "cnames": [],
    "fingerprinting": 1,
    "resources": [
        {
            "rule": "growdiaries\\.com\\/",
            "cookies": 0.0000511,
            "fingerprinting": 0,
            "subdomains": [],
            "apis": {},
            "sites": 8,
            "prevalence": 0.0000584,
            "cnames": [],
            "type": "Document"
        },
        {
            "rule": "growdiaries\\.com\\/temp\\/js\\/bcc02f305135b856be2dbf4fdfeb85c92253468\\.js",
            "cookies": 0,
            "fingerprinting": 1,
            "subdomains": [],
            "apis": {
                "Date.prototype.getTime": 4
            },
            "sites": 7,
            "prevalence": 0.0000511,
            "cnames": [],
            "type": "Script"
        }
    ],
    "categories": [],
    "performance": {},
    "cookies": 0.0000584,
    "types": {
        "Document": 8,
        "Script": 7
    }
}