{
    "domain": "lotlinx.com",
    "owner": {},
    "source": [
        "DuckDuckGo-US"
    ],
    "prevalence": 0.000873,
    "sites": 115,
    "subdomains": [
        "cm2",
        "cm"
    ],
    "cnames": [],
    "fingerprinting": 1,
    "resources": [
        {
            "rule": "lotlinx\\.com\\/live\\/141000\\/sync",
            "cookies": 0.000608,
            "fingerprinting": 0,
            "subdomains": [
                "cm2"
            ],
            "apis": {},
            "sites": 80,
            "prevalence": 0.000608,
            "cnames": [],
            "responseHashes": [
                "b1442e85b03bdcaf66dc58c7abb98745dd2687d86350be9a298a1d9382ac849b"
            ],
            "type": "Image",
            "exampleSites": [
                "www.newsnationnow.com",
                "www.cbs17.com",
                "www.yourcentralvalley.com",
                "www.wpri.com",
                "www.wjtv.com",
                "www.ksn.com",
                "www.wjhl.com",
                "www.mywabashvalley.com",
                "www.wearecentralpa.com",
                "www.wkrn.com",
                "www.wkbn.com",
                "www.centralillinoisproud.com",
                "www.kron4.com",
                "www.wivb.com",
                "www.localsyr.com",
                "www.wwlp.com",
                "www.wspa.com",
                "www.wtrf.com",
                "www.wavy.com",
                "www.kark.com"
            ]
        },
        {
            "rule": "lotlinx\\.com\\/live\\/141000\\/hmr",
            "cookies": 0.000608,
            "fingerprinting": 0,
            "subdomains": [
                "cm"
            ],
            "apis": {},
            "sites": 80,
            "prevalence": 0.000608,
            "cnames": [],
            "responseHashes": [
                "b1442e85b03bdcaf66dc58c7abb98745dd2687d86350be9a298a1d9382ac849b"
            ],
            "type": "Image",
            "exampleSites": [
                "www.wkbn.com",
                "www.woodtv.com",
                "www.wrbl.com",
                "www.8newsnow.com",
                "www.pahomepage.com",
                "www.wwlp.com",
                "www.kget.com",
                "www.yourerie.com",
                "www.wbtw.com",
                "www.wavy.com",
                "www.tristatehomepage.com",
                "www.wearecentralpa.com",
                "www.wtnh.com",
                "www.wate.com",
                "www.news10.com",
                "www.wowktv.com",
                "www.myarklamiss.com",
                "www.ksnt.com",
                "www.wearegreenbay.com",
                "www.ktsm.com"
            ]
        }
    ],
    "categories": [],
    "performance": {
        "time": 0,
        "size": 0,
        "cpu": 0,
        "cache": 0
    },
    "cookies": 0.000873,
    "types": {
        "Image": 160
    }
}