{
    "domain": "adition.com",
    "owner": {
        "name": "Virtual Minds AG",
        "displayName": "Virtual Minds",
        "privacyPolicy": "https://www.virtualminds.de/en/",
        "url": "http://virtualminds.de"
    },
    "source": [
        "DuckDuckGo-NL"
    ],
    "prevalence": 0.00773,
    "sites": 77,
    "subdomains": [
        "dsp.adfarm1",
        "ad4.adfarm1",
        "ad11.adfarm1",
        "imagesrv"
    ],
    "cnames": [],
    "fingerprinting": 1,
    "resources": [
        {
            "rule": "adition\\.com\\/cookie\\/",
            "cookies": 0.00482,
            "fingerprinting": 0,
            "subdomains": [
                "dsp.adfarm1"
            ],
            "apis": {},
            "sites": 52,
            "prevalence": 0.00522,
            "cnames": [],
            "responseHashes": [
                "1866961a029c65376fefb7f2ba1e6187e09ff50ea58d97dedfd72c197947d002"
            ],
            "type": "Document",
            "firstPartyCookies": {},
            "firstPartyCookiesSent": {},
            "exampleSites": [
                "ok.ru",
                "www.azlyrics.com",
                "www.digitaltrends.com",
                "www.mirror.co.uk",
                "www.tasteofhome.com",
                "www.urbandictionary.com",
                "www.zerohedge.com",
                "investorplace.com",
                "www.scoopwhoop.com",
                "www.dailystar.co.uk",
                "howtodoinjava.com",
                "www.seznam.cz",
                "nl.ccm.net",
                "www.beurs.nl",
                "www.nirsoft.net",
                "itigic.com",
                "www.poftut.com",
                "geekflare.com",
                "kimwelling.com",
                "worldpopulationreview.com"
            ]
        },
        {
            "rule": "adition\\.com\\/cookie\\/",
            "cookies": 0.00261,
            "fingerprinting": 0,
            "subdomains": [
                "dsp.adfarm1"
            ],
            "apis": {},
            "sites": 28,
            "prevalence": 0.00281,
            "cnames": [],
            "responseHashes": [],
            "type": "Image",
            "firstPartyCookies": {},
            "firstPartyCookiesSent": {},
            "exampleSites": [
                "www.azlyrics.com",
                "huispedia.nl",
                "echo.msk.ru",
                "www.voetbalkalender.nl",
                "www.carid.com",
                "geekflare.com",
                "www.systutorials.com",
                "www.belkin.com",
                "www.mediamarkt.com",
                "www.hetnoordbrabantsmuseum.nl",
                "www.linksys.com",
                "www.okokorecepten.nl",
                "www.brusselstimes.com",
                "creatiefdenken.com",
                "bulbagarden.net",
                "itigic.com",
                "www.crypto-insiders.nl",
                "www.redvoicemedia.com",
                "www.kookfans.nl",
                "mediabiasfactcheck.com"
            ]
        },
        {
            "rule": "adition\\.com\\/track",
            "cookies": 0.0001,
            "fingerprinting": 0,
            "subdomains": [
                "ad4.adfarm1"
            ],
            "apis": {},
            "sites": 2,
            "prevalence": 0.000201,
            "cnames": [],
            "responseHashes": [],
            "type": "Document",
            "firstPartyCookies": {},
            "firstPartyCookiesSent": {},
            "exampleSites": [
                "harley-davidson.com",
                "www.harley-davidson.com"
            ]
        },
        {
            "rule": "adition\\.com\\/tagging",
            "cookies": 0.000201,
            "fingerprinting": 0,
            "subdomains": [
                "ad11.adfarm1"
            ],
            "apis": {},
            "sites": 2,
            "prevalence": 0.000201,
            "cnames": [],
            "responseHashes": [],
            "type": "Image",
            "firstPartyCookies": {},
            "firstPartyCookiesSent": {},
            "exampleSites": [
                "peek-cloppenburg.nl",
                "www.peek-cloppenburg.nl"
            ]
        },
        {
            "rule": "adition\\.com\\/1x1\\.gif",
            "cookies": 0,
            "fingerprinting": 0,
            "subdomains": [
                "imagesrv"
            ],
            "apis": {},
            "sites": 3,
            "prevalence": 0.000301,
            "cnames": [],
            "responseHashes": [
                "5fb3bdb7f966c852579fb6b0574517445d5b2d171c804d66227ee67b1bffca9c"
            ],
            "type": "Image",
            "firstPartyCookies": {},
            "firstPartyCookiesSent": {},
            "exampleSites": [
                "peek-cloppenburg.nl",
                "www.peek-cloppenburg.nl",
                "www.t-online.de"
            ]
        },
        {
            "rule": "adition\\.com\\/js\\/srp\\.js",
            "cookies": 0,
            "fingerprinting": 1,
            "subdomains": [
                "imagesrv"
            ],
            "apis": {
                "Navigator.prototype.userAgent": 2,
                "Navigator.prototype.appVersion": 2,
                "Navigator.prototype.plugins": 2,
                "Screen.prototype.width": 2,
                "Screen.prototype.height": 2,
                "Date.prototype.getTime": 1
            },
            "sites": 2,
            "prevalence": 0.000201,
            "cnames": [],
            "responseHashes": [
                "e3ec02b8a59d3125d803c8d4dbf6ed079b100cc03de24eb535410f958afd7672"
            ],
            "type": "Script",
            "firstPartyCookies": {},
            "firstPartyCookiesSent": {},
            "exampleSites": [
                "t-online.de",
                "www.transfermarkt.com"
            ]
        }
    ],
    "categories": [
        "Ad Motivated Tracking",
        "Advertising"
    ],
    "performance": {
        "time": 1,
        "size": 1,
        "cpu": 2,
        "cache": 3
    },
    "cookies": 0.00703,
    "types": {
        "Document": 54,
        "Image": 33,
        "Script": 2
    },
    "nameservers": [
        "ns3.dnsimple.com",
        "ns4.dnsimple.com",
        "ns1.dnsimple.com",
        "ns2.dnsimple.com"
    ]
}