{
    "domain": "wheelwheel.space",
    "owner": {},
    "source": [
        "DuckDuckGo-NL"
    ],
    "prevalence": 0.000406,
    "sites": 4,
    "subdomains": [],
    "cnames": [],
    "fingerprinting": 0,
    "resources": [
        {
            "rule": "wheelwheel\\.space\\/iframe\\/5ef9c7f4d8a33",
            "cookies": 0.000304,
            "fingerprinting": 0,
            "subdomains": [],
            "apis": {},
            "sites": 3,
            "prevalence": 0.000304,
            "cnames": [],
            "responseHashes": [
                "7dbb8a93e05f3b2984bfdfd4ed34efd0639f5a9a4791fae6b2159c2fcddfcc75"
            ],
            "type": "Document",
            "exampleSites": [
                "cartoonprn.com",
                "komikhentai.online",
                "komikhentai.me"
            ]
        }
    ],
    "categories": [],
    "performance": {
        "time": 0,
        "size": 0,
        "cpu": 0,
        "cache": 0
    },
    "cookies": 0.000406,
    "types": {
        "Document": 3
    }
}